accelbyte_py_sdk/api/dsmc/__init__.py
accelbyte_py_sdk/api/dsmc/errors.py
accelbyte_py_sdk/api/dsmc/models/__init__.py
accelbyte_py_sdk/api/dsmc/models/log_app_message_declaration.py
accelbyte_py_sdk/api/dsmc/models/models_add_buffer_request.py
accelbyte_py_sdk/api/dsmc/models/models_add_buffer_response.py
accelbyte_py_sdk/api/dsmc/models/models_allocation_event.py
accelbyte_py_sdk/api/dsmc/models/models_claim_session_request.py
accelbyte_py_sdk/api/dsmc/models/models_count_server_response.py
accelbyte_py_sdk/api/dsmc/models/models_count_session_response.py
accelbyte_py_sdk/api/dsmc/models/models_create_deployment_override_request.py
accelbyte_py_sdk/api/dsmc/models/models_create_deployment_request.py
accelbyte_py_sdk/api/dsmc/models/models_create_dsm_config_request.py
accelbyte_py_sdk/api/dsmc/models/models_create_image_patch_request.py
accelbyte_py_sdk/api/dsmc/models/models_create_image_request.py
accelbyte_py_sdk/api/dsmc/models/models_create_pod_config_request.py
accelbyte_py_sdk/api/dsmc/models/models_create_port_request.py
accelbyte_py_sdk/api/dsmc/models/models_create_region_override_request.py
accelbyte_py_sdk/api/dsmc/models/models_create_repository_request.py
accelbyte_py_sdk/api/dsmc/models/models_create_session_request.py
accelbyte_py_sdk/api/dsmc/models/models_default_provider.py
accelbyte_py_sdk/api/dsmc/models/models_delete_zombie_request.py
accelbyte_py_sdk/api/dsmc/models/models_deployment_config_override.py
accelbyte_py_sdk/api/dsmc/models/models_deployment_with_override.py
accelbyte_py_sdk/api/dsmc/models/models_deregister_local_server_request.py
accelbyte_py_sdk/api/dsmc/models/models_detailed_count_server_response.py
accelbyte_py_sdk/api/dsmc/models/models_ds_heartbeat_request.py
accelbyte_py_sdk/api/dsmc/models/models_dsm_config_record.py
accelbyte_py_sdk/api/dsmc/models/models_get_image_detail_response.py
accelbyte_py_sdk/api/dsmc/models/models_get_image_limit_response.py
accelbyte_py_sdk_service_dsmc-0.18.0.dist-info/METADATA
accelbyte_py_sdk_service_dsmc-0.18.0.dist-info/WHEEL
accelbyte_py_sdk_service_dsmc-0.18.0.dist-info/top_level.txt
accelbyte_py_sdk_service_dsmc-0.18.0.dist-info/RECORD
